{
  "headers": {
    "X-Content-Type-Options": "nosniff",
    "X-Frame-Options": "DENY",
    "X-XSS-Protection": "1; mode=block",
    "Strict-Transport-Security": "max-age=31536000; includeSubDomains",
    "Content-Security-Policy": "default-src 'self'; script-src 'self' 'unsafe-inline' 'unsafe-eval'; style-src 'self' 'unsafe-inline'; img-src 'self' data: https:; font-src 'self' data:; connect-src 'self' https:; frame-ancestors 'none';",
    "Referrer-Policy": "strict-origin-when-cross-origin",
    "Permissions-Policy": "geolocation=(), microphone=(), camera=()"
  },
  "rateLimit": {
    "windowMs": 900000,
    "max": 100,
    "message": "Too many requests from this IP, please try again later."
  },
  "csrf": {
    "cookie": {
      "httpOnly": true,
      "secure": false,
      "sameSite": "strict"
    }
  }
}